bandit_multi_format/__init__.py
bandit_multi_format-0.1.1.dist-info/WHEEL
bandit_multi_format-0.1.1.dist-info/entry_points.txt
bandit_multi_format-0.1.1.dist-info/METADATA
bandit_multi_format-0.1.1.dist-info/RECORD
