Metadata-Version: 2.3
Name: bandit-multi-format
Version: 0.1.1
Summary: Bandit formatter that writes the same report in multiple formats (json, txt, xml).
Keywords: bandit,formatter,security,sast
Author: Elazar
Author-email: Elazar <elazarcoh@gmail.com>
License: MIT License
Classifier: Programming Language :: Python :: 3
Classifier: Programming Language :: Python :: 3.10
Classifier: Programming Language :: Python :: 3.11
Classifier: Programming Language :: Python :: 3.12
Classifier: Programming Language :: Python :: 3.13
Classifier: Development Status :: 4 - Beta
Classifier: Intended Audience :: Developers
Classifier: Topic :: Security
Classifier: License :: OSI Approved :: MIT License
Classifier: Operating System :: OS Independent
Requires-Python: >=3.10
Project-URL: Homepage, https://github.com/elazarcoh/bandit-multi-format
Project-URL: Source, https://github.com/elazarcoh/bandit-multi-format
Project-URL: Tracker, https://github.com/elazarcoh/bandit-multi-format/issues
